liblds/__init__.py
liblds/ldsbus_commands.py
liblds/ldsbus_constants.py
liblds/ldsbus_errors.py
liblds/ldsbus_interface.py
liblds/ldsbus_messages.py
liblds/ldsu_descriptors.py
liblds/ldsu_response.py
liblds/utils.py
pyliblds-0.0.0.1.dist-info/LICENSE
pyliblds-0.0.0.1.dist-info/METADATA
pyliblds-0.0.0.1.dist-info/WHEEL
pyliblds-0.0.0.1.dist-info/top_level.txt
pyliblds-0.0.0.1.dist-info/RECORD
