Metadata-Version: 2.1
Name: pyliblds
Version: 0.0.0.1
Summary: Python SDK for LDSU Devices
Home-page: UNKNOWN
Author: Prabhakaran Dharmarajan
Author-email: prabhakaran.d@brtchhip.com
License: MIT
Keywords: pyliblds
Platform: UNKNOWN
Classifier: Development Status :: 3 - Alpha
Classifier: Intended Audience :: Developers
Classifier: License :: OSI Approved :: MIT License
Classifier: Programming Language :: Python :: 3
License-File: LICENSE
